[{"Year":2015,"Value":0.1,"Series":"Proportion (%)"},{"Year":2016,"Value":0.4,"Series":"Proportion (%)"},{"Year":2017,"Value":0.1,"Series":"Proportion (%)"},{"Year":2018,"Value":0.2,"Series":"Proportion (%)"},{"Year":2019,"Value":0.2,"Series":"Proportion (%)"},{"Year":2020,"Value":1.2,"Series":"Proportion (%)"},{"Year":2021,"Value":0.8,"Series":"Proportion (%)"},{"Year":2022,"Value":1.4,"Series":"Proportion (%)"},{"Year":2015,"Value":66.0,"Series":"Remittances (million vatu)"},{"Year":2016,"Value":273.0,"Series":"Remittances (million vatu)"},{"Year":2017,"Value":88.0,"Series":"Remittances (million vatu)"},{"Year":2018,"Value":149.0,"Series":"Remittances (million vatu)"},{"Year":2019,"Value":123.0,"Series":"Remittances (million vatu)"},{"Year":2020,"Value":800.0,"Series":"Remittances (million vatu)"},{"Year":2021,"Value":515.0,"Series":"Remittances (million vatu)"},{"Year":2022,"Value":984.0,"Series":"Remittances (million vatu)"},{"Year":2015,"Value":61500.0,"Series":"GDP Constant (million vatu)"},{"Year":2016,"Value":63635.0,"Series":"GDP Constant (million vatu)"},{"Year":2017,"Value":66443.0,"Series":"GDP Constant (million vatu)"},{"Year":2018,"Value":68370.0,"Series":"GDP Constant (million vatu)"},{"Year":2019,"Value":70586.0,"Series":"GDP Constant (million vatu)"},{"Year":2020,"Value":67062.0,"Series":"GDP Constant (million vatu)"},{"Year":2021,"Value":66021.0,"Series":"GDP Constant (million vatu)"},{"Year":2022,"Value":69445.0,"Series":"GDP Constant (million vatu)"}]